cuprocell/__init__.py
cuprocell/executable.py
cuprocell/pathutils.py
cuprocell-0.0.2.data/scripts/cuprocell-hmsbuild.bat
cuprocell-0.0.2.data/scripts/cuprocell-install.bat
cuprocell-0.0.2.data/scripts/cuprocell-install.sh
cuprocell-0.0.2.dist-info/LICENSE.txt
cuprocell-0.0.2.dist-info/METADATA
cuprocell-0.0.2.dist-info/WHEEL
cuprocell-0.0.2.dist-info/top_level.txt
cuprocell-0.0.2.dist-info/RECORD
